spacearth/metrics/__init__.py
spacearth/metrics/aws.py
spacearth/metrics/metric_server.py
spacearth/metrics/noop.py
spacearth/metrics/prometheus.py
spacearth_metrics-1.0.1.dist-info/LICENSE
spacearth_metrics-1.0.1.dist-info/METADATA
spacearth_metrics-1.0.1.dist-info/WHEEL
spacearth_metrics-1.0.1.dist-info/RECORD
