Metadata-Version: 2.3
Name: spacearth-metrics
Version: 1.0.1
Summary: Gather metrics from Python services using either AWS CloudWatch or Prometheus.
License: Apache-2.0
Keywords: metrics,cloudwatch,prometheus,monitoring,observability
Author: Michelle Laurenti
Author-email: michelle.laurenti@spacearthnav.it
Requires-Python: >=3.10
Classifier: Development Status :: 4 - Beta
Classifier: Intended Audience :: Developers
Classifier: License :: OSI Approved :: Apache Software License
Classifier: Operating System :: OS Independent
Classifier: Programming Language :: Python :: 3
Classifier: Programming Language :: Python :: 3.10
Classifier: Programming Language :: Python :: 3.11
Classifier: Programming Language :: Python :: 3.12
Classifier: Topic :: Software Development :: Libraries :: Python Modules
Classifier: Topic :: System :: Monitoring
Requires-Dist: boto3 (>=1.42.0,<2.0.0)
Requires-Dist: prometheus-python (>=1.0.3,<2.0.0)
Project-URL: Homepage, https://github.com/Spacearth-NAV/metrics-lib
Project-URL: Issues, https://github.com/Spacearth-NAV/metrics-lib/issues
Project-URL: Repository, https://github.com/Spacearth-NAV/metrics-lib
